excelfred.py
excelfred-0.1.4.dist-info/METADATA
excelfred-0.1.4.dist-info/WHEEL
excelfred-0.1.4.dist-info/licenses/LICENSE
excelfred-0.1.4.dist-info/RECORD
