Metadata-Version: 2.4
Name: excelfred
Version: 0.1.4
Summary: Recreate Microsoft Excel 514 formulas using NumPy and Pandas, Contact: https://www.linkedin.com/in/samuel-raj23
Author-email: SAMUEL RAJ P <samuelraj239@email.com>
License: MIT License
License-File: LICENSE
Requires-Python: >=3.7
Requires-Dist: numpy
Requires-Dist: pandas
